tygle_sheets/__init__.py
tygle_sheets/rest/__init__.py
tygle_sheets/rest/spreadsheets.py
tygle_sheets/rest/values.py
tygle_sheets/sheets.py
tygle_sheets/types/__init__.py
tygle_sheets/types/enums/__init__.py
tygle_sheets/types/enums/date_time_render_option.py
tygle_sheets/types/enums/dimension.py
tygle_sheets/types/enums/error_type.py
tygle_sheets/types/enums/insert_data_option.py
tygle_sheets/types/enums/value_input_option.py
tygle_sheets/types/enums/value_render_option.py
tygle_sheets/types/resources/__init__.py
tygle_sheets/types/resources/spreadsheets/__init__.py
tygle_sheets/types/resources/spreadsheets/cell_data.py
tygle_sheets/types/resources/spreadsheets/chains/__init__.py
tygle_sheets/types/resources/spreadsheets/chains/values.py
tygle_sheets/types/resources/spreadsheets/error_value.py
tygle_sheets/types/resources/spreadsheets/extended_value.py
tygle_sheets/types/resources/spreadsheets/grid_data.py
tygle_sheets/types/resources/spreadsheets/grid_range.py
tygle_sheets/types/resources/spreadsheets/row_data.py
tygle_sheets/types/resources/spreadsheets/sheet.py
tygle_sheets/types/resources/spreadsheets/sheet_properties.py
tygle_sheets/types/resources/spreadsheets/spreadsheet.py
tygle_sheets/types/resources/spreadsheets/spreadsheet_properties.py
tygle_sheets/types/resources/values/__init__.py
tygle_sheets/types/resources/values/value_range.py
tygle_sheets/types/responses/__init__.py
tygle_sheets/types/responses/update_values_response.py
tygle_sheets/types/responses/values/__init__.py
tygle_sheets/types/responses/values/append_response.py
tygle_sheets-0.1.3.dist-info/WHEEL
tygle_sheets-0.1.3.dist-info/METADATA
tygle_sheets-0.1.3.dist-info/RECORD
